sphinx_extractor/__init__.py
sphinx_extractor/directives/__init__.py
sphinx_extractor/directives/extract.py
sphinx_extractor-0.1.0.dist-info/LICENSE
sphinx_extractor-0.1.0.dist-info/WHEEL
sphinx_extractor-0.1.0.dist-info/METADATA
sphinx_extractor-0.1.0.dist-info/RECORD
